MANIFEST.in
README.rst
setup.cfg
setup.py
Xenops.egg-info/PKG-INFO
Xenops.egg-info/SOURCES.txt
Xenops.egg-info/dependency_links.txt
Xenops.egg-info/top_level.txt
xenops/__init__.py
xenops/app.py
xenops/cli.py
xenops/conf.py
xenops/connector.py
xenops/service.py
xenops/data/__init__.py
xenops/data/converter.py
xenops/data/types/__init__.py
xenops/data/types/product.py