Metadata-Version: 1.1
Name: Xenops
Version: 0.0.1
Summary: Xenops is a simple program to sync data like (customers/products) between different systems
Home-page: https://github.com/krukas/Xenops
Author: Maikel Martens
Author-email: maikel@martens.me
License: GPL3
Download-URL: https://github.com/krukas/Xenops/releases/tag/0.0.1
Keywords: Xenops,Connector,Enterprise Service Bus,ESB
Platform: UNKNOWN
Classifier: License :: OSI Approved :: GNU General Public License v3 (GPLv3)
Classifier: Programming Language :: Python :: 3
